.gitignore
.travis.yml
MANIFEST.in
README.md
deploy.json
install_git_hooks
setup.py
test
consulconf/__init__.py
consulconf/__main__.py
consulconf/main.py
consulconf/util.py
consulconf.egg-info/PKG-INFO
consulconf.egg-info/SOURCES.txt
consulconf.egg-info/dependency_links.txt
consulconf.egg-info/entry_points.txt
consulconf.egg-info/requires.txt
consulconf.egg-info/top_level.txt