Metadata-Version: 1.0
Name: consulconf
Version: 0.0.10
Summary: Code to configure consul key:value store for applications
Home-page: https://github.com/sailthru/consulconf
Author: Alex Gaudio
Author-email: agaudio@sailthru.com
License: UNKNOWN
Platform: UNKNOWN
